{
  "a_comp_cor_00": {
    "CumulativeVarianceExplained": 0.0238944713,
    "Mask": "combined",
    "Method": "aCompCor",
    "Retained": true,
    "SingularValue": 235.2053975845,
    "VarianceExplained": 0.0238944713
  },
  "a_comp_cor_01": {
    "CumulativeVarianceExplained": 0.0404818717,
    "Mask": "combined",
    "Method": "aCompCor",
    "Retained": true,
    "SingularValue": 195.9691618493,
    "VarianceExplained": 0.0165874004
  },
  "a_comp_cor_02": {
    "CumulativeVarianceExplained": 0.0541986246,
    "Mask": "combined",
    "Method": "aCompCor",
    "Retained": true,
    "SingularValue": 178.2067823469,
    "VarianceExplained": 0.0137167529
  },
  "a_comp_cor_03": {
    "CumulativeVarianceExplained": 0.0665034203,
    "Mask": "combined",
    "Method": "aCompCor",
    "Retained": true,
    "SingularValue": 168.7857491846,
    "VarianceExplained": 0.0123047957
  },
  "a_comp_cor_04": {
    "CumulativeVarianceExplained": 0.0780056031,
    "Mask": "combined",
    "Method": "aCompCor",
    "Retained": true,
    "SingularValue": 163.1881820379,
    "VarianceExplained": 0.0115021828
  },
  "a_comp_cor_05": {
    "CumulativeVarianceExplained": 0.0885625726,
    "Mask": "combined",
    "Method": "aCompCor",
    "Retained": true,
    "SingularValue": 156.3393150699,
    "VarianceExplained": 0.0105569695
  },
  "a_comp_cor_06": {
    "CumulativeVarianceExplained": 0.0982389506,
    "Mask": "combined",
    "Method": "aCompCor",
    "Retained": true,
    "SingularValue": 149.6769698893,
    "VarianceExplained": 0.0096763779
  },
  "a_comp_cor_07": {
    "CumulativeVarianceExplained": 0.1066098971,
    "Mask": "combined",
    "Method": "aCompCor",
    "Retained": true,
    "SingularValue": 139.2149432241,
    "VarianceExplained": 0.0083709465
  },
  "a_comp_cor_08": {
    "CumulativeVarianceExplained": 0.1147904383,
    "Mask": "combined",
    "Method": "aCompCor",
    "Retained": true,
    "SingularValue": 137.6225469102,
    "VarianceExplained": 0.0081805413
  },
  "a_comp_cor_09": {
    "CumulativeVarianceExplained": 0.1226157055,
    "Mask": "combined",
    "Method": "aCompCor",
    "Retained": true,
    "SingularValue": 134.6009599334,
    "VarianceExplained": 0.0078252671
  },
  "a_comp_cor_10": {
    "CumulativeVarianceExplained": 0.1301120629,
    "Mask": "combined",
    "Method": "aCompCor",
    "Retained": true,
    "SingularValue": 131.74183723,
    "VarianceExplained": 0.0074963575
  },
  "a_comp_cor_11": {
    "CumulativeVarianceExplained": 0.1375396175,
    "Mask": "combined",
    "Method": "aCompCor",
    "Retained": true,
    "SingularValue": 131.135868373,
    "VarianceExplained": 0.0074275546
  },
  "a_comp_cor_12": {
    "CumulativeVarianceExplained": 0.1449114056,
    "Mask": "combined",
    "Method": "aCompCor",
    "Retained": true,
    "SingularValue": 130.6426530912,
    "VarianceExplained": 0.0073717881
  },
  "a_comp_cor_13": {
    "CumulativeVarianceExplained": 0.1521535847,
    "Mask": "combined",
    "Method": "aCompCor",
    "Retained": true,
    "SingularValue": 129.4890972289,
    "VarianceExplained": 0.0072421791
  },
  "a_comp_cor_14": {
    "CumulativeVarianceExplained": 0.1592554281,
    "Mask": "combined",
    "Method": "aCompCor",
    "Retained": true,
    "SingularValue": 128.2283682415,
    "VarianceExplained": 0.0071018434
  },
  "a_comp_cor_15": {
    "CumulativeVarianceExplained": 0.1662690054,
    "Mask": "combined",
    "Method": "aCompCor",
    "Retained": true,
    "SingularValue": 127.429027201,
    "VarianceExplained": 0.0070135774
  },
  "a_comp_cor_16": {
    "CumulativeVarianceExplained": 0.1731838744,
    "Mask": "combined",
    "Method": "aCompCor",
    "Retained": true,
    "SingularValue": 126.5291376809,
    "VarianceExplained": 0.006914869
  },
  "a_comp_cor_17": {
    "CumulativeVarianceExplained": 0.1800011119,
    "Mask": "combined",
    "Method": "aCompCor",
    "Retained": true,
    "SingularValue": 125.6327256971,
    "VarianceExplained": 0.0068172375
  },
  "a_comp_cor_18": {
    "CumulativeVarianceExplained": 0.1867961603,
    "Mask": "combined",
    "Method": "aCompCor",
    "Retained": true,
    "SingularValue": 125.4281023136,
    "VarianceExplained": 0.0067950485
  },
  "a_comp_cor_19": {
    "CumulativeVarianceExplained": 0.1935475856,
    "Mask": "combined",
    "Method": "aCompCor",
    "Retained": true,
    "SingularValue": 125.0248385177,
    "VarianceExplained": 0.0067514252
  },
  "a_comp_cor_20": {
    "CumulativeVarianceExplained": 0.2002649912,
    "Mask": "combined",
    "Method": "aCompCor",
    "Retained": true,
    "SingularValue": 124.7094479465,
    "VarianceExplained": 0.0067174056
  },
  "a_comp_cor_21": {
    "CumulativeVarianceExplained": 0.2069300365,
    "Mask": "combined",
    "Method": "aCompCor",
    "Retained": true,
    "SingularValue": 124.2224604571,
    "VarianceExplained": 0.0066650454
  },
  "a_comp_cor_22": {
    "CumulativeVarianceExplained": 0.2135723172,
    "Mask": "combined",
    "Method": "aCompCor",
    "Retained": true,
    "SingularValue": 124.0101359377,
    "VarianceExplained": 0.0066422807
  },
  "a_comp_cor_23": {
    "CumulativeVarianceExplained": 0.2201818275,
    "Mask": "combined",
    "Method": "aCompCor",
    "Retained": true,
    "SingularValue": 123.703848944,
    "VarianceExplained": 0.0066095103
  },
  "a_comp_cor_24": {
    "CumulativeVarianceExplained": 0.2267309933,
    "Mask": "combined",
    "Method": "aCompCor",
    "Retained": true,
    "SingularValue": 123.1378489773,
    "VarianceExplained": 0.0065491658
  },
  "a_comp_cor_25": {
    "CumulativeVarianceExplained": 0.2332499831,
    "Mask": "combined",
    "Method": "aCompCor",
    "Retained": true,
    "SingularValue": 122.8538358378,
    "VarianceExplained": 0.0065189898
  },
  "a_comp_cor_26": {
    "CumulativeVarianceExplained": 0.2397288422,
    "Mask": "combined",
    "Method": "aCompCor",
    "Retained": true,
    "SingularValue": 122.4751102944,
    "VarianceExplained": 0.0064788591
  },
  "a_comp_cor_27": {
    "CumulativeVarianceExplained": 0.2461604435,
    "Mask": "combined",
    "Method": "aCompCor",
    "Retained": true,
    "SingularValue": 122.0276162613,
    "VarianceExplained": 0.0064316013
  },
  "a_comp_cor_28": {
    "CumulativeVarianceExplained": 0.2525401716,
    "Mask": "combined",
    "Method": "aCompCor",
    "Retained": true,
    "SingularValue": 121.5345223915,
    "VarianceExplained": 0.0063797282
  },
  "a_comp_cor_29": {
    "CumulativeVarianceExplained": 0.2588928882,
    "Mask": "combined",
    "Method": "aCompCor",
    "Retained": true,
    "SingularValue": 121.2769621458,
    "VarianceExplained": 0.0063527165
  },
  "a_comp_cor_30": {
    "CumulativeVarianceExplained": 0.2652439738,
    "Mask": "combined",
    "Method": "aCompCor",
    "Retained": true,
    "SingularValue": 121.2613933279,
    "VarianceExplained": 0.0063510856
  },
  "a_comp_cor_31": {
    "CumulativeVarianceExplained": 0.2715570535,
    "Mask": "combined",
    "Method": "aCompCor",
    "Retained": true,
    "SingularValue": 120.8980254904,
    "VarianceExplained": 0.0063130797
  },
  "a_comp_cor_32": {
    "CumulativeVarianceExplained": 0.2778565923,
    "Mask": "combined",
    "Method": "aCompCor",
    "Retained": true,
    "SingularValue": 120.768299123,
    "VarianceExplained": 0.0062995388
  },
  "a_comp_cor_33": {
    "CumulativeVarianceExplained": 0.2841482687,
    "Mask": "combined",
    "Method": "aCompCor",
    "Retained": true,
    "SingularValue": 120.6929101143,
    "VarianceExplained": 0.0062916764
  },
  "a_comp_cor_34": {
    "CumulativeVarianceExplained": 0.2903656127,
    "Mask": "combined",
    "Method": "aCompCor",
    "Retained": true,
    "SingularValue": 119.9778349708,
    "VarianceExplained": 0.006217344
  },
  "a_comp_cor_35": {
    "CumulativeVarianceExplained": 0.2965661079,
    "Mask": "combined",
    "Method": "aCompCor",
    "Retained": true,
    "SingularValue": 119.8151566017,
    "VarianceExplained": 0.0062004952
  },
  "a_comp_cor_36": {
    "CumulativeVarianceExplained": 0.3027540872,
    "Mask": "combined",
    "Method": "aCompCor",
    "Retained": true,
    "SingularValue": 119.69416992,
    "VarianceExplained": 0.0061879793
  },
  "a_comp_cor_37": {
    "CumulativeVarianceExplained": 0.3089205824,
    "Mask": "combined",
    "Method": "aCompCor",
    "Retained": true,
    "SingularValue": 119.4862054356,
    "VarianceExplained": 0.0061664952
  },
  "a_comp_cor_38": {
    "CumulativeVarianceExplained": 0.3150765171,
    "Mask": "combined",
    "Method": "aCompCor",
    "Retained": true,
    "SingularValue": 119.3838482017,
    "VarianceExplained": 0.0061559347
  },
  "a_comp_cor_39": {
    "CumulativeVarianceExplained": 0.3211976486,
    "Mask": "combined",
    "Method": "aCompCor",
    "Retained": true,
    "SingularValue": 119.0458951561,
    "VarianceExplained": 0.0061211315
  },
  "a_comp_cor_40": {
    "CumulativeVarianceExplained": 0.3273147524,
    "Mask": "combined",
    "Method": "aCompCor",
    "Retained": true,
    "SingularValue": 119.006722999,
    "VarianceExplained": 0.0061171038
  },
  "a_comp_cor_41": {
    "CumulativeVarianceExplained": 0.3333980907,
    "Mask": "combined",
    "Method": "aCompCor",
    "Retained": true,
    "SingularValue": 118.6778191554,
    "VarianceExplained": 0.0060833383
  },
  "a_comp_cor_42": {
    "CumulativeVarianceExplained": 0.3394496274,
    "Mask": "combined",
    "Method": "aCompCor",
    "Retained": true,
    "SingularValue": 118.3672090955,
    "VarianceExplained": 0.0060515367
  },
  "a_comp_cor_43": {
    "CumulativeVarianceExplained": 0.3454657907,
    "Mask": "combined",
    "Method": "aCompCor",
    "Retained": true,
    "SingularValue": 118.0207520098,
    "VarianceExplained": 0.0060161633
  },
  "a_comp_cor_44": {
    "CumulativeVarianceExplained": 0.3514809222,
    "Mask": "combined",
    "Method": "aCompCor",
    "Retained": true,
    "SingularValue": 118.0106312075,
    "VarianceExplained": 0.0060151315
  },
  "a_comp_cor_45": {
    "CumulativeVarianceExplained": 0.357464141,
    "Mask": "combined",
    "Method": "aCompCor",
    "Retained": true,
    "SingularValue": 117.6971685903,
    "VarianceExplained": 0.0059832188
  },
  "a_comp_cor_46": {
    "CumulativeVarianceExplained": 0.3634267708,
    "Mask": "combined",
    "Method": "aCompCor",
    "Retained": true,
    "SingularValue": 117.4944886646,
    "VarianceExplained": 0.0059626298
  },
  "a_comp_cor_47": {
    "CumulativeVarianceExplained": 0.3693781765,
    "Mask": "combined",
    "Method": "aCompCor",
    "Retained": true,
    "SingularValue": 117.3838492269,
    "VarianceExplained": 0.0059514056
  },
  "a_comp_cor_48": {
    "CumulativeVarianceExplained": 0.3753255756,
    "Mask": "combined",
    "Method": "aCompCor",
    "Retained": true,
    "SingularValue": 117.3443313263,
    "VarianceExplained": 0.0059473992
  },
  "a_comp_cor_49": {
    "CumulativeVarianceExplained": 0.3812627272,
    "Mask": "combined",
    "Method": "aCompCor",
    "Retained": true,
    "SingularValue": 117.2431935018,
    "VarianceExplained": 0.0059371516
  },
  "a_comp_cor_50": {
    "CumulativeVarianceExplained": 0.387167256,
    "Mask": "combined",
    "Method": "aCompCor",
    "Retained": true,
    "SingularValue": 116.920642644,
    "VarianceExplained": 0.0059045288
  },
  "a_comp_cor_51": {
    "CumulativeVarianceExplained": 0.3930520301,
    "Mask": "combined",
    "Method": "aCompCor",
    "Retained": true,
    "SingularValue": 116.7248896584,
    "VarianceExplained": 0.0058847742
  },
  "a_comp_cor_52": {
    "CumulativeVarianceExplained": 0.3989258849,
    "Mask": "combined",
    "Method": "aCompCor",
    "Retained": true,
    "SingularValue": 116.616546094,
    "VarianceExplained": 0.0058738548
  },
  "a_comp_cor_53": {
    "CumulativeVarianceExplained": 0.4047792876,
    "Mask": "combined",
    "Method": "aCompCor",
    "Retained": true,
    "SingularValue": 116.4133462495,
    "VarianceExplained": 0.0058534027
  },
  "a_comp_cor_54": {
    "CumulativeVarianceExplained": 0.4105962235,
    "Mask": "combined",
    "Method": "aCompCor",
    "Retained": true,
    "SingularValue": 116.0501505476,
    "VarianceExplained": 0.0058169358
  },
  "a_comp_cor_55": {
    "CumulativeVarianceExplained": 0.4164060019,
    "Mask": "combined",
    "Method": "aCompCor",
    "Retained": true,
    "SingularValue": 115.9787314134,
    "VarianceExplained": 0.0058097784
  },
  "a_comp_cor_56": {
    "CumulativeVarianceExplained": 0.4222103504,
    "Mask": "combined",
    "Method": "aCompCor",
    "Retained": true,
    "SingularValue": 115.9245219978,
    "VarianceExplained": 0.0058043486
  },
  "a_comp_cor_57": {
    "CumulativeVarianceExplained": 0.4280019021,
    "Mask": "combined",
    "Method": "aCompCor",
    "Retained": true,
    "SingularValue": 115.7966620776,
    "VarianceExplained": 0.0057915517
  },
  "a_comp_cor_58": {
    "CumulativeVarianceExplained": 0.4337754433,
    "Mask": "combined",
    "Method": "aCompCor",
    "Retained": true,
    "SingularValue": 115.6164694544,
    "VarianceExplained": 0.0057735411
  },
  "a_comp_cor_59": {
    "CumulativeVarianceExplained": 0.4395249954,
    "Mask": "combined",
    "Method": "aCompCor",
    "Retained": true,
    "SingularValue": 115.3760271117,
    "VarianceExplained": 0.0057495522
  },
  "a_comp_cor_60": {
    "CumulativeVarianceExplained": 0.4452678846,
    "Mask": "combined",
    "Method": "aCompCor",
    "Retained": true,
    "SingularValue": 115.3091546164,
    "VarianceExplained": 0.0057428892
  },
  "a_comp_cor_61": {
    "CumulativeVarianceExplained": 0.4509907149,
    "Mask": "combined",
    "Method": "aCompCor",
    "Retained": true,
    "SingularValue": 115.107601734,
    "VarianceExplained": 0.0057228303
  },
  "a_comp_cor_62": {
    "CumulativeVarianceExplained": 0.4566998011,
    "Mask": "combined",
    "Method": "aCompCor",
    "Retained": true,
    "SingularValue": 114.9692956899,
    "VarianceExplained": 0.0057090862
  },
  "a_comp_cor_63": {
    "CumulativeVarianceExplained": 0.4624025304,
    "Mask": "combined",
    "Method": "aCompCor",
    "Retained": true,
    "SingularValue": 114.9052713152,
    "VarianceExplained": 0.0057027294
  },
  "a_comp_cor_64": {
    "CumulativeVarianceExplained": 0.4680846051,
    "Mask": "combined",
    "Method": "aCompCor",
    "Retained": true,
    "SingularValue": 114.6969947556,
    "VarianceExplained": 0.0056820747
  },
  "a_comp_cor_65": {
    "CumulativeVarianceExplained": 0.4737575105,
    "Mask": "combined",
    "Method": "aCompCor",
    "Retained": true,
    "SingularValue": 114.6044135347,
    "VarianceExplained": 0.0056729054
  },
  "a_comp_cor_66": {
    "CumulativeVarianceExplained": 0.4794243279,
    "Mask": "combined",
    "Method": "aCompCor",
    "Retained": true,
    "SingularValue": 114.5429010734,
    "VarianceExplained": 0.0056668173
  },
  "a_comp_cor_67": {
    "CumulativeVarianceExplained": 0.4850766771,
    "Mask": "combined",
    "Method": "aCompCor",
    "Retained": true,
    "SingularValue": 114.3965859456,
    "VarianceExplained": 0.0056523492
  },
  "a_comp_cor_68": {
    "CumulativeVarianceExplained": 0.4907154148,
    "Mask": "combined",
    "Method": "aCompCor",
    "Retained": true,
    "SingularValue": 114.2587633159,
    "VarianceExplained": 0.0056387377
  },
  "a_comp_cor_69": {
    "CumulativeVarianceExplained": 0.4963437119,
    "Mask": "combined",
    "Method": "aCompCor",
    "Retained": true,
    "SingularValue": 114.1529337907,
    "VarianceExplained": 0.0056282971
  },
  "a_comp_cor_70": {
    "CumulativeVarianceExplained": 0.501968055,
    "Mask": "combined",
    "Method": "aCompCor",
    "Retained": true,
    "SingularValue": 114.1128299068,
    "VarianceExplained": 0.0056243431
  },
  "c_comp_cor_00": {
    "CumulativeVarianceExplained": 0.0408250485,
    "Mask": "CSF",
    "Method": "aCompCor",
    "Retained": true,
    "SingularValue": 57.1210952661,
    "VarianceExplained": 0.0408250485
  },
  "c_comp_cor_01": {
    "CumulativeVarianceExplained": 0.0701753696,
    "Mask": "CSF",
    "Method": "aCompCor",
    "Retained": true,
    "SingularValue": 48.4328025898,
    "VarianceExplained": 0.0293503211
  },
  "c_comp_cor_02": {
    "CumulativeVarianceExplained": 0.0961269934,
    "Mask": "CSF",
    "Method": "aCompCor",
    "Retained": true,
    "SingularValue": 45.5423503197,
    "VarianceExplained": 0.0259516237
  },
  "c_comp_cor_03": {
    "CumulativeVarianceExplained": 0.1183667916,
    "Mask": "CSF",
    "Method": "aCompCor",
    "Retained": true,
    "SingularValue": 42.1598049287,
    "VarianceExplained": 0.0222397982
  },
  "c_comp_cor_04": {
    "CumulativeVarianceExplained": 0.1361737539,
    "Mask": "CSF",
    "Method": "aCompCor",
    "Retained": true,
    "SingularValue": 37.7248994978,
    "VarianceExplained": 0.0178069623
  },
  "c_comp_cor_05": {
    "CumulativeVarianceExplained": 0.1522630067,
    "Mask": "CSF",
    "Method": "aCompCor",
    "Retained": true,
    "SingularValue": 35.8592424285,
    "VarianceExplained": 0.0160892529
  },
  "c_comp_cor_06": {
    "CumulativeVarianceExplained": 0.1679062429,
    "Mask": "CSF",
    "Method": "aCompCor",
    "Retained": true,
    "SingularValue": 35.3587148557,
    "VarianceExplained": 0.0156432361
  },
  "c_comp_cor_07": {
    "CumulativeVarianceExplained": 0.1821886467,
    "Mask": "CSF",
    "Method": "aCompCor",
    "Retained": true,
    "SingularValue": 33.7857703723,
    "VarianceExplained": 0.0142824038
  },
  "c_comp_cor_08": {
    "CumulativeVarianceExplained": 0.195855702,
    "Mask": "CSF",
    "Method": "aCompCor",
    "Retained": true,
    "SingularValue": 33.049937902,
    "VarianceExplained": 0.0136670553
  },
  "c_comp_cor_09": {
    "CumulativeVarianceExplained": 0.2088903102,
    "Mask": "CSF",
    "Method": "aCompCor",
    "Retained": true,
    "SingularValue": 32.2761824988,
    "VarianceExplained": 0.0130346082
  },
  "c_comp_cor_10": {
    "CumulativeVarianceExplained": 0.2216898734,
    "Mask": "CSF",
    "Method": "aCompCor",
    "Retained": true,
    "SingularValue": 31.9838504642,
    "VarianceExplained": 0.0127995632
  },
  "c_comp_cor_11": {
    "CumulativeVarianceExplained": 0.2340798581,
    "Mask": "CSF",
    "Method": "aCompCor",
    "Retained": true,
    "SingularValue": 31.4679575487,
    "VarianceExplained": 0.0123899846
  },
  "c_comp_cor_12": {
    "CumulativeVarianceExplained": 0.2460200666,
    "Mask": "CSF",
    "Method": "aCompCor",
    "Retained": true,
    "SingularValue": 30.8915093225,
    "VarianceExplained": 0.0119402086
  },
  "c_comp_cor_13": {
    "CumulativeVarianceExplained": 0.2576568346,
    "Mask": "CSF",
    "Method": "aCompCor",
    "Retained": true,
    "SingularValue": 30.4964550794,
    "VarianceExplained": 0.011636768
  },
  "c_comp_cor_14": {
    "CumulativeVarianceExplained": 0.2690287268,
    "Mask": "CSF",
    "Method": "aCompCor",
    "Retained": true,
    "SingularValue": 30.1473774533,
    "VarianceExplained": 0.0113718922
  },
  "c_comp_cor_15": {
    "CumulativeVarianceExplained": 0.2803177226,
    "Mask": "CSF",
    "Method": "aCompCor",
    "Retained": true,
    "SingularValue": 30.0372955324,
    "VarianceExplained": 0.0112889958
  },
  "c_comp_cor_16": {
    "CumulativeVarianceExplained": 0.2912567398,
    "Mask": "CSF",
    "Method": "aCompCor",
    "Retained": true,
    "SingularValue": 29.5680255172,
    "VarianceExplained": 0.0109390172
  },
  "c_comp_cor_17": {
    "CumulativeVarianceExplained": 0.302121275,
    "Mask": "CSF",
    "Method": "aCompCor",
    "Retained": true,
    "SingularValue": 29.4671915358,
    "VarianceExplained": 0.0108645351
  },
  "c_comp_cor_18": {
    "CumulativeVarianceExplained": 0.3128711399,
    "Mask": "CSF",
    "Method": "aCompCor",
    "Retained": true,
    "SingularValue": 29.31127274,
    "VarianceExplained": 0.010749865
  },
  "c_comp_cor_19": {
    "CumulativeVarianceExplained": 0.3234895328,
    "Mask": "CSF",
    "Method": "aCompCor",
    "Retained": true,
    "SingularValue": 29.1314811652,
    "VarianceExplained": 0.0106183929
  },
  "c_comp_cor_20": {
    "CumulativeVarianceExplained": 0.3339996223,
    "Mask": "CSF",
    "Method": "aCompCor",
    "Retained": true,
    "SingularValue": 28.9825357027,
    "VarianceExplained": 0.0105100895
  },
  "c_comp_cor_21": {
    "CumulativeVarianceExplained": 0.3443179966,
    "Mask": "CSF",
    "Method": "aCompCor",
    "Retained": true,
    "SingularValue": 28.7169828626,
    "VarianceExplained": 0.0103183742
  },
  "c_comp_cor_22": {
    "CumulativeVarianceExplained": 0.3544845425,
    "Mask": "CSF",
    "Method": "aCompCor",
    "Retained": true,
    "SingularValue": 28.5049238109,
    "VarianceExplained": 0.0101665459
  },
  "c_comp_cor_23": {
    "CumulativeVarianceExplained": 0.3645497561,
    "Mask": "CSF",
    "Method": "aCompCor",
    "Retained": true,
    "SingularValue": 28.3625105807,
    "VarianceExplained": 0.0100652137
  },
  "c_comp_cor_24": {
    "CumulativeVarianceExplained": 0.3744312953,
    "Mask": "CSF",
    "Method": "aCompCor",
    "Retained": true,
    "SingularValue": 28.1025332413,
    "VarianceExplained": 0.0098815392
  },
  "c_comp_cor_25": {
    "CumulativeVarianceExplained": 0.3842126248,
    "Mask": "CSF",
    "Method": "aCompCor",
    "Retained": true,
    "SingularValue": 27.9596748441,
    "VarianceExplained": 0.0097813295
  },
  "c_comp_cor_26": {
    "CumulativeVarianceExplained": 0.3939168333,
    "Mask": "CSF",
    "Method": "aCompCor",
    "Retained": true,
    "SingularValue": 27.8492325234,
    "VarianceExplained": 0.0097042085
  },
  "c_comp_cor_27": {
    "CumulativeVarianceExplained": 0.4033256564,
    "Mask": "CSF",
    "Method": "aCompCor",
    "Retained": true,
    "SingularValue": 27.4221070274,
    "VarianceExplained": 0.009408823
  },
  "c_comp_cor_28": {
    "CumulativeVarianceExplained": 0.4126086885,
    "Mask": "CSF",
    "Method": "aCompCor",
    "Retained": true,
    "SingularValue": 27.2381808646,
    "VarianceExplained": 0.0092830322
  },
  "c_comp_cor_29": {
    "CumulativeVarianceExplained": 0.4218274817,
    "Mask": "CSF",
    "Method": "aCompCor",
    "Retained": true,
    "SingularValue": 27.1437725777,
    "VarianceExplained": 0.0092187932
  },
  "c_comp_cor_30": {
    "CumulativeVarianceExplained": 0.4309081071,
    "Mask": "CSF",
    "Method": "aCompCor",
    "Retained": true,
    "SingularValue": 26.9395943198,
    "VarianceExplained": 0.0090806254
  },
  "c_comp_cor_31": {
    "CumulativeVarianceExplained": 0.4399631492,
    "Mask": "CSF",
    "Method": "aCompCor",
    "Retained": true,
    "SingularValue": 26.901618481,
    "VarianceExplained": 0.0090550421
  },
  "c_comp_cor_32": {
    "CumulativeVarianceExplained": 0.4489505096,
    "Mask": "CSF",
    "Method": "aCompCor",
    "Retained": true,
    "SingularValue": 26.8008921134,
    "VarianceExplained": 0.0089873604
  },
  "c_comp_cor_33": {
    "CumulativeVarianceExplained": 0.4576871379,
    "Mask": "CSF",
    "Method": "aCompCor",
    "Retained": true,
    "SingularValue": 26.4243979525,
    "VarianceExplained": 0.0087366283
  },
  "c_comp_cor_34": {
    "CumulativeVarianceExplained": 0.4662416026,
    "Mask": "CSF",
    "Method": "aCompCor",
    "Retained": true,
    "SingularValue": 26.1474649705,
    "VarianceExplained": 0.0085544647
  },
  "c_comp_cor_35": {
    "CumulativeVarianceExplained": 0.4747153484,
    "Mask": "CSF",
    "Method": "aCompCor",
    "Retained": true,
    "SingularValue": 26.0238104847,
    "VarianceExplained": 0.0084737458
  },
  "c_comp_cor_36": {
    "CumulativeVarianceExplained": 0.4830805187,
    "Mask": "CSF",
    "Method": "aCompCor",
    "Retained": true,
    "SingularValue": 25.8565493551,
    "VarianceExplained": 0.0083651703
  },
  "c_comp_cor_37": {
    "CumulativeVarianceExplained": 0.491396866,
    "Mask": "CSF",
    "Method": "aCompCor",
    "Retained": true,
    "SingularValue": 25.780983412,
    "VarianceExplained": 0.0083163473
  },
  "c_comp_cor_38": {
    "CumulativeVarianceExplained": 0.4995550171,
    "Mask": "CSF",
    "Method": "aCompCor",
    "Retained": true,
    "SingularValue": 25.5345990371,
    "VarianceExplained": 0.008158151
  },
  "c_comp_cor_39": {
    "CumulativeVarianceExplained": 0.5076683638,
    "Mask": "CSF",
    "Method": "aCompCor",
    "Retained": true,
    "SingularValue": 25.4643849106,
    "VarianceExplained": 0.0081133467
  },
  "dropped_0": {
    "CumulativeVarianceExplained": 0.2360842088,
    "Mask": "Edge",
    "Method": "EdgeRegressor",
    "Retained": false,
    "SingularValue": 113.4417665297,
    "VarianceExplained": 0.0064719314
  },
  "dropped_1": {
    "CumulativeVarianceExplained": 0.2425203844,
    "Mask": "Edge",
    "Method": "EdgeRegressor",
    "Retained": false,
    "SingularValue": 113.1279628025,
    "VarianceExplained": 0.0064361755
  },
  "dropped_10": {
    "CumulativeVarianceExplained": 0.298973744,
    "Mask": "Edge",
    "Method": "EdgeRegressor",
    "Retained": false,
    "SingularValue": 111.0034395101,
    "VarianceExplained": 0.0061967049
  },
  "dropped_100": {
    "CumulativeVarianceExplained": 0.7882931304,
    "Mask": "Edge",
    "Method": "EdgeRegressor",
    "Retained": false,
    "SingularValue": 97.9106127308,
    "VarianceExplained": 0.0048211149
  },
  "dropped_101": {
    "CumulativeVarianceExplained": 0.793090977,
    "Mask": "Edge",
    "Method": "EdgeRegressor",
    "Retained": false,
    "SingularValue": 97.6740525176,
    "VarianceExplained": 0.0047978466
  },
  "dropped_102": {
    "CumulativeVarianceExplained": 0.7978787935,
    "Mask": "Edge",
    "Method": "EdgeRegressor",
    "Retained": false,
    "SingularValue": 97.5719026315,
    "VarianceExplained": 0.0047878165
  },
  "dropped_103": {
    "CumulativeVarianceExplained": 0.8026470372,
    "Mask": "Edge",
    "Method": "EdgeRegressor",
    "Retained": false,
    "SingularValue": 97.3722594095,
    "VarianceExplained": 0.0047682437
  },
  "dropped_104": {
    "CumulativeVarianceExplained": 0.8074101779,
    "Mask": "Edge",
    "Method": "EdgeRegressor",
    "Retained": false,
    "SingularValue": 97.3201415654,
    "VarianceExplained": 0.0047631407
  },
  "dropped_105": {
    "CumulativeVarianceExplained": 0.8121528213,
    "Mask": "Edge",
    "Method": "EdgeRegressor",
    "Retained": false,
    "SingularValue": 97.1105170172,
    "VarianceExplained": 0.0047426435
  },
  "dropped_106": {
    "CumulativeVarianceExplained": 0.8168670689,
    "Mask": "Edge",
    "Method": "EdgeRegressor",
    "Retained": false,
    "SingularValue": 96.8193627407,
    "VarianceExplained": 0.0047142476
  },
  "dropped_107": {
    "CumulativeVarianceExplained": 0.8215767903,
    "Mask": "Edge",
    "Method": "EdgeRegressor",
    "Retained": false,
    "SingularValue": 96.7728737635,
    "VarianceExplained": 0.0047097214
  },
  "dropped_108": {
    "CumulativeVarianceExplained": 0.8262776105,
    "Mask": "Edge",
    "Method": "EdgeRegressor",
    "Retained": false,
    "SingularValue": 96.6813807219,
    "VarianceExplained": 0.0047008201
  },
  "dropped_109": {
    "CumulativeVarianceExplained": 0.8309632933,
    "Mask": "Edge",
    "Method": "EdgeRegressor",
    "Retained": false,
    "SingularValue": 96.5255916569,
    "VarianceExplained": 0.0046856829
  },
  "dropped_11": {
    "CumulativeVarianceExplained": 0.3051589859,
    "Mask": "Edge",
    "Method": "EdgeRegressor",
    "Retained": false,
    "SingularValue": 110.9007222151,
    "VarianceExplained": 0.006185242
  },
  "dropped_110": {
    "CumulativeVarianceExplained": 0.8356365489,
    "Mask": "Edge",
    "Method": "EdgeRegressor",
    "Retained": false,
    "SingularValue": 96.3975044776,
    "VarianceExplained": 0.0046732555
  },
  "dropped_111": {
    "CumulativeVarianceExplained": 0.8402904478,
    "Mask": "Edge",
    "Method": "EdgeRegressor",
    "Retained": false,
    "SingularValue": 96.1976580698,
    "VarianceExplained": 0.0046538989
  },
  "dropped_112": {
    "CumulativeVarianceExplained": 0.8449316309,
    "Mask": "Edge",
    "Method": "EdgeRegressor",
    "Retained": false,
    "SingularValue": 96.0661488973,
    "VarianceExplained": 0.0046411832
  },
  "dropped_113": {
    "CumulativeVarianceExplained": 0.8495517987,
    "Mask": "Edge",
    "Method": "EdgeRegressor",
    "Retained": false,
    "SingularValue": 95.8484068138,
    "VarianceExplained": 0.0046201677
  },
  "dropped_114": {
    "CumulativeVarianceExplained": 0.8541654564,
    "Mask": "Edge",
    "Method": "EdgeRegressor",
    "Retained": false,
    "SingularValue": 95.780856127,
    "VarianceExplained": 0.0046136578
  },
  "dropped_115": {
    "CumulativeVarianceExplained": 0.8587641325,
    "Mask": "Edge",
    "Method": "EdgeRegressor",
    "Retained": false,
    "SingularValue": 95.6252176244,
    "VarianceExplained": 0.0045986761
  },
  "dropped_116": {
    "CumulativeVarianceExplained": 0.8633579645,
    "Mask": "Edge",
    "Method": "EdgeRegressor",
    "Retained": false,
    "SingularValue": 95.5748401317,
    "VarianceExplained": 0.004593832
  },
  "dropped_117": {
    "CumulativeVarianceExplained": 0.8679428885,
    "Mask": "Edge",
    "Method": "EdgeRegressor",
    "Retained": false,
    "SingularValue": 95.4821307155,
    "VarianceExplained": 0.0045849241
  },
  "dropped_118": {
    "CumulativeVarianceExplained": 0.8725023466,
    "Mask": "Edge",
    "Method": "EdgeRegressor",
    "Retained": false,
    "SingularValue": 95.2165933093,
    "VarianceExplained": 0.004559458
  },
  "dropped_119": {
    "CumulativeVarianceExplained": 0.8770450171,
    "Mask": "Edge",
    "Method": "EdgeRegressor",
    "Retained": false,
    "SingularValue": 95.0411420751,
    "VarianceExplained": 0.0045426705
  },
  "dropped_12": {
    "CumulativeVarianceExplained": 0.3112949437,
    "Mask": "Edge",
    "Method": "EdgeRegressor",
    "Retained": false,
    "SingularValue": 110.45800841,
    "VarianceExplained": 0.0061359578
  },
  "dropped_120": {
    "CumulativeVarianceExplained": 0.8815800541,
    "Mask": "Edge",
    "Method": "EdgeRegressor",
    "Retained": false,
    "SingularValue": 94.9612549526,
    "VarianceExplained": 0.004535037
  },
  "dropped_121": {
    "CumulativeVarianceExplained": 0.8860931464,
    "Mask": "Edge",
    "Method": "EdgeRegressor",
    "Retained": false,
    "SingularValue": 94.7312201945,
    "VarianceExplained": 0.0045130922
  },
  "dropped_122": {
    "CumulativeVarianceExplained": 0.8906050923,
    "Mask": "Edge",
    "Method": "EdgeRegressor",
    "Retained": false,
    "SingularValue": 94.7191884935,
    "VarianceExplained": 0.0045119459
  },
  "dropped_123": {
    "CumulativeVarianceExplained": 0.8951010955,
    "Mask": "Edge",
    "Method": "EdgeRegressor",
    "Retained": false,
    "SingularValue": 94.5516989545,
    "VarianceExplained": 0.0044960033
  },
  "dropped_124": {
    "CumulativeVarianceExplained": 0.8995787517,
    "Mask": "Edge",
    "Method": "EdgeRegressor",
    "Retained": false,
    "SingularValue": 94.3585804,
    "VarianceExplained": 0.0044776562
  },
  "dropped_125": {
    "CumulativeVarianceExplained": 0.9040365718,
    "Mask": "Edge",
    "Method": "EdgeRegressor",
    "Retained": false,
    "SingularValue": 94.1493432968,
    "VarianceExplained": 0.0044578201
  },
  "dropped_126": {
    "CumulativeVarianceExplained": 0.9084857683,
    "Mask": "Edge",
    "Method": "EdgeRegressor",
    "Retained": false,
    "SingularValue": 94.0582341848,
    "VarianceExplained": 0.0044491965
  },
  "dropped_127": {
    "CumulativeVarianceExplained": 0.9129205965,
    "Mask": "Edge",
    "Method": "EdgeRegressor",
    "Retained": false,
    "SingularValue": 93.9062351455,
    "VarianceExplained": 0.0044348282
  },
  "dropped_128": {
    "CumulativeVarianceExplained": 0.9173477019,
    "Mask": "Edge",
    "Method": "EdgeRegressor",
    "Retained": false,
    "SingularValue": 93.824434583,
    "VarianceExplained": 0.0044271054
  },
  "dropped_129": {
    "CumulativeVarianceExplained": 0.921761522,
    "Mask": "Edge",
    "Method": "EdgeRegressor",
    "Retained": false,
    "SingularValue": 93.6835498268,
    "VarianceExplained": 0.00441382
  },
  "dropped_13": {
    "CumulativeVarianceExplained": 0.3173978015,
    "Mask": "Edge",
    "Method": "EdgeRegressor",
    "Retained": false,
    "SingularValue": 110.1596765106,
    "VarianceExplained": 0.0061028578
  },
  "dropped_130": {
    "CumulativeVarianceExplained": 0.9261538046,
    "Mask": "Edge",
    "Method": "EdgeRegressor",
    "Retained": false,
    "SingularValue": 93.454704402,
    "VarianceExplained": 0.0043922827
  },
  "dropped_131": {
    "CumulativeVarianceExplained": 0.9305320287,
    "Mask": "Edge",
    "Method": "EdgeRegressor",
    "Retained": false,
    "SingularValue": 93.3050223819,
    "VarianceExplained": 0.0043782241
  },
  "dropped_132": {
    "CumulativeVarianceExplained": 0.934900488,
    "Mask": "Edge",
    "Method": "EdgeRegressor",
    "Retained": false,
    "SingularValue": 93.200913758,
    "VarianceExplained": 0.0043684592
  },
  "dropped_133": {
    "CumulativeVarianceExplained": 0.9392443482,
    "Mask": "Edge",
    "Method": "EdgeRegressor",
    "Retained": false,
    "SingularValue": 92.9381343366,
    "VarianceExplained": 0.0043438603
  },
  "dropped_134": {
    "CumulativeVarianceExplained": 0.9435565906,
    "Mask": "Edge",
    "Method": "EdgeRegressor",
    "Retained": false,
    "SingularValue": 92.5992801518,
    "VarianceExplained": 0.0043122424
  },
  "dropped_135": {
    "CumulativeVarianceExplained": 0.9478515422,
    "Mask": "Edge",
    "Method": "EdgeRegressor",
    "Retained": false,
    "SingularValue": 92.413445261,
    "VarianceExplained": 0.0042949515
  },
  "dropped_136": {
    "CumulativeVarianceExplained": 0.9521145812,
    "Mask": "Edge",
    "Method": "EdgeRegressor",
    "Retained": false,
    "SingularValue": 92.0694779582,
    "VarianceExplained": 0.004263039
  },
  "dropped_137": {
    "CumulativeVarianceExplained": 0.9563612392,
    "Mask": "Edge",
    "Method": "EdgeRegressor",
    "Retained": false,
    "SingularValue": 91.8924163744,
    "VarianceExplained": 0.004246658
  },
  "dropped_138": {
    "CumulativeVarianceExplained": 0.9605801268,
    "Mask": "Edge",
    "Method": "EdgeRegressor",
    "Retained": false,
    "SingularValue": 91.5914647325,
    "VarianceExplained": 0.0042188876
  },
  "dropped_139": {
    "CumulativeVarianceExplained": 0.9647816509,
    "Mask": "Edge",
    "Method": "EdgeRegressor",
    "Retained": false,
    "SingularValue": 91.4027908801,
    "VarianceExplained": 0.0042015241
  },
  "dropped_14": {
    "CumulativeVarianceExplained": 0.3234856102,
    "Mask": "Edge",
    "Method": "EdgeRegressor",
    "Retained": false,
    "SingularValue": 110.0237704426,
    "VarianceExplained": 0.0060878087
  },
  "dropped_140": {
    "CumulativeVarianceExplained": 0.9689715593,
    "Mask": "Edge",
    "Method": "EdgeRegressor",
    "Retained": false,
    "SingularValue": 91.2763550482,
    "VarianceExplained": 0.0041899084
  },
  "dropped_141": {
    "CumulativeVarianceExplained": 0.9731346289,
    "Mask": "Edge",
    "Method": "EdgeRegressor",
    "Retained": false,
    "SingularValue": 90.9835471919,
    "VarianceExplained": 0.0041630696
  },
  "dropped_142": {
    "CumulativeVarianceExplained": 0.9772901203,
    "Mask": "Edge",
    "Method": "EdgeRegressor",
    "Retained": false,
    "SingularValue": 90.9006988297,
    "VarianceExplained": 0.0041554914
  },
  "dropped_143": {
    "CumulativeVarianceExplained": 0.9814227856,
    "Mask": "Edge",
    "Method": "EdgeRegressor",
    "Retained": false,
    "SingularValue": 90.6506953508,
    "VarianceExplained": 0.0041326652
  },
  "dropped_144": {
    "CumulativeVarianceExplained": 0.985518142,
    "Mask": "Edge",
    "Method": "EdgeRegressor",
    "Retained": false,
    "SingularValue": 90.2405810463,
    "VarianceExplained": 0.0040953565
  },
  "dropped_145": {
    "CumulativeVarianceExplained": 0.9895422288,
    "Mask": "Edge",
    "Method": "EdgeRegressor",
    "Retained": false,
    "SingularValue": 89.4519255487,
    "VarianceExplained": 0.0040240867
  },
  "dropped_146": {
    "CumulativeVarianceExplained": 0.993499024,
    "Mask": "Edge",
    "Method": "EdgeRegressor",
    "Retained": false,
    "SingularValue": 88.7008565101,
    "VarianceExplained": 0.0039567952
  },
  "dropped_147": {
    "CumulativeVarianceExplained": 0.9971901262,
    "Mask": "Edge",
    "Method": "EdgeRegressor",
    "Retained": false,
    "SingularValue": 85.6710442042,
    "VarianceExplained": 0.0036911022
  },
  "dropped_148": {
    "CumulativeVarianceExplained": 1.0,
    "Mask": "Edge",
    "Method": "EdgeRegressor",
    "Retained": false,
    "SingularValue": 74.7479759911,
    "VarianceExplained": 0.0028098738
  },
  "dropped_149": {
    "CumulativeVarianceExplained": 1.0,
    "Mask": "Edge",
    "Method": "EdgeRegressor",
    "Retained": false,
    "SingularValue": 0.0,
    "VarianceExplained": 0.0
  },
  "dropped_15": {
    "CumulativeVarianceExplained": 0.3295537777,
    "Mask": "Edge",
    "Method": "EdgeRegressor",
    "Retained": false,
    "SingularValue": 109.8461420072,
    "VarianceExplained": 0.0060681675
  },
  "dropped_150": {
    "CumulativeVarianceExplained": 1.0,
    "Mask": "Edge",
    "Method": "EdgeRegressor",
    "Retained": false,
    "SingularValue": 0.0,
    "VarianceExplained": 0.0
  },
  "dropped_151": {
    "CumulativeVarianceExplained": 1.0,
    "Mask": "Edge",
    "Method": "EdgeRegressor",
    "Retained": false,
    "SingularValue": 0.0,
    "VarianceExplained": 0.0
  },
  "dropped_152": {
    "CumulativeVarianceExplained": 1.0,
    "Mask": "Edge",
    "Method": "EdgeRegressor",
    "Retained": false,
    "SingularValue": 0.0,
    "VarianceExplained": 0.0
  },
  "dropped_153": {
    "CumulativeVarianceExplained": 1.0,
    "Mask": "Edge",
    "Method": "EdgeRegressor",
    "Retained": false,
    "SingularValue": 0.0,
    "VarianceExplained": 0.0
  },
  "dropped_16": {
    "CumulativeVarianceExplained": 0.3356190406,
    "Mask": "Edge",
    "Method": "EdgeRegressor",
    "Retained": false,
    "SingularValue": 109.8198491057,
    "VarianceExplained": 0.0060652629
  },
  "dropped_17": {
    "CumulativeVarianceExplained": 0.3416498089,
    "Mask": "Edge",
    "Method": "EdgeRegressor",
    "Retained": false,
    "SingularValue": 109.507118028,
    "VarianceExplained": 0.0060307683
  },
  "dropped_18": {
    "CumulativeVarianceExplained": 0.3476674577,
    "Mask": "Edge",
    "Method": "EdgeRegressor",
    "Retained": false,
    "SingularValue": 109.3879402983,
    "VarianceExplained": 0.0060176488
  },
  "dropped_19": {
    "CumulativeVarianceExplained": 0.3536563996,
    "Mask": "Edge",
    "Method": "EdgeRegressor",
    "Retained": false,
    "SingularValue": 109.1267138548,
    "VarianceExplained": 0.0059889419
  },
  "dropped_2": {
    "CumulativeVarianceExplained": 0.2489124213,
    "Mask": "Edge",
    "Method": "EdgeRegressor",
    "Retained": false,
    "SingularValue": 112.7393858879,
    "VarianceExplained": 0.0063920369
  },
  "dropped_20": {
    "CumulativeVarianceExplained": 0.359626945,
    "Mask": "Edge",
    "Method": "EdgeRegressor",
    "Retained": false,
    "SingularValue": 108.958980118,
    "VarianceExplained": 0.0059705454
  },
  "dropped_21": {
    "CumulativeVarianceExplained": 0.365583497,
    "Mask": "Edge",
    "Method": "EdgeRegressor",
    "Retained": false,
    "SingularValue": 108.831219342,
    "VarianceExplained": 0.005956552
  },
  "dropped_22": {
    "CumulativeVarianceExplained": 0.3715306846,
    "Mask": "Edge",
    "Method": "EdgeRegressor",
    "Retained": false,
    "SingularValue": 108.7456383016,
    "VarianceExplained": 0.0059471876
  },
  "dropped_23": {
    "CumulativeVarianceExplained": 0.3774701488,
    "Mask": "Edge",
    "Method": "EdgeRegressor",
    "Retained": false,
    "SingularValue": 108.6750029498,
    "VarianceExplained": 0.0059394642
  },
  "dropped_24": {
    "CumulativeVarianceExplained": 0.3833718143,
    "Mask": "Edge",
    "Method": "EdgeRegressor",
    "Retained": false,
    "SingularValue": 108.3286480097,
    "VarianceExplained": 0.0059016655
  },
  "dropped_25": {
    "CumulativeVarianceExplained": 0.3892688118,
    "Mask": "Edge",
    "Method": "EdgeRegressor",
    "Retained": false,
    "SingularValue": 108.2857970444,
    "VarianceExplained": 0.0058969975
  },
  "dropped_26": {
    "CumulativeVarianceExplained": 0.3951331444,
    "Mask": "Edge",
    "Method": "EdgeRegressor",
    "Retained": false,
    "SingularValue": 107.9854704065,
    "VarianceExplained": 0.0058643326
  },
  "dropped_27": {
    "CumulativeVarianceExplained": 0.4009822379,
    "Mask": "Edge",
    "Method": "EdgeRegressor",
    "Retained": false,
    "SingularValue": 107.8450736216,
    "VarianceExplained": 0.0058490936
  },
  "dropped_28": {
    "CumulativeVarianceExplained": 0.4068221131,
    "Mask": "Edge",
    "Method": "EdgeRegressor",
    "Retained": false,
    "SingularValue": 107.7600559501,
    "VarianceExplained": 0.0058398751
  },
  "dropped_29": {
    "CumulativeVarianceExplained": 0.4126472303,
    "Mask": "Edge",
    "Method": "EdgeRegressor",
    "Retained": false,
    "SingularValue": 107.623810023,
    "VarianceExplained": 0.0058251172
  },
  "dropped_3": {
    "CumulativeVarianceExplained": 0.2552672575,
    "Mask": "Edge",
    "Method": "EdgeRegressor",
    "Retained": false,
    "SingularValue": 112.4108436362,
    "VarianceExplained": 0.0063548362
  },
  "dropped_30": {
    "CumulativeVarianceExplained": 0.418438714,
    "Mask": "Edge",
    "Method": "EdgeRegressor",
    "Retained": false,
    "SingularValue": 107.3126565456,
    "VarianceExplained": 0.0057914837
  },
  "dropped_31": {
    "CumulativeVarianceExplained": 0.4242234724,
    "Mask": "Edge",
    "Method": "EdgeRegressor",
    "Retained": false,
    "SingularValue": 107.2503308664,
    "VarianceExplained": 0.0057847584
  },
  "dropped_32": {
    "CumulativeVarianceExplained": 0.4299861382,
    "Mask": "Edge",
    "Method": "EdgeRegressor",
    "Retained": false,
    "SingularValue": 107.0453346083,
    "VarianceExplained": 0.0057626658
  },
  "dropped_33": {
    "CumulativeVarianceExplained": 0.4357449177,
    "Mask": "Edge",
    "Method": "EdgeRegressor",
    "Retained": false,
    "SingularValue": 107.0092326933,
    "VarianceExplained": 0.0057587794
  },
  "dropped_34": {
    "CumulativeVarianceExplained": 0.4414892684,
    "Mask": "Edge",
    "Method": "EdgeRegressor",
    "Retained": false,
    "SingularValue": 106.8750921686,
    "VarianceExplained": 0.0057443508
  },
  "dropped_35": {
    "CumulativeVarianceExplained": 0.4472188622,
    "Mask": "Edge",
    "Method": "EdgeRegressor",
    "Retained": false,
    "SingularValue": 106.7377252676,
    "VarianceExplained": 0.0057295938
  },
  "dropped_36": {
    "CumulativeVarianceExplained": 0.4529352006,
    "Mask": "Edge",
    "Method": "EdgeRegressor",
    "Retained": false,
    "SingularValue": 106.6141850615,
    "VarianceExplained": 0.0057163384
  },
  "dropped_37": {
    "CumulativeVarianceExplained": 0.4586270908,
    "Mask": "Edge",
    "Method": "EdgeRegressor",
    "Retained": false,
    "SingularValue": 106.3859522211,
    "VarianceExplained": 0.0056918902
  },
  "dropped_38": {
    "CumulativeVarianceExplained": 0.4643069465,
    "Mask": "Edge",
    "Method": "EdgeRegressor",
    "Retained": false,
    "SingularValue": 106.2734244271,
    "VarianceExplained": 0.0056798556
  },
  "dropped_39": {
    "CumulativeVarianceExplained": 0.4699797228,
    "Mask": "Edge",
    "Method": "EdgeRegressor",
    "Retained": false,
    "SingularValue": 106.2071754608,
    "VarianceExplained": 0.0056727764
  },
  "dropped_4": {
    "CumulativeVarianceExplained": 0.2615694131,
    "Mask": "Edge",
    "Method": "EdgeRegressor",
    "Retained": false,
    "SingularValue": 111.9439402971,
    "VarianceExplained": 0.0063021556
  },
  "dropped_40": {
    "CumulativeVarianceExplained": 0.4756304169,
    "Mask": "Edge",
    "Method": "EdgeRegressor",
    "Retained": false,
    "SingularValue": 106.00025848,
    "VarianceExplained": 0.0056506941
  },
  "dropped_41": {
    "CumulativeVarianceExplained": 0.4812469067,
    "Mask": "Edge",
    "Method": "EdgeRegressor",
    "Retained": false,
    "SingularValue": 105.6789564946,
    "VarianceExplained": 0.0056164899
  },
  "dropped_42": {
    "CumulativeVarianceExplained": 0.4868494515,
    "Mask": "Edge",
    "Method": "EdgeRegressor",
    "Retained": false,
    "SingularValue": 105.5476806942,
    "VarianceExplained": 0.0056025448
  },
  "dropped_43": {
    "CumulativeVarianceExplained": 0.4924417562,
    "Mask": "Edge",
    "Method": "EdgeRegressor",
    "Retained": false,
    "SingularValue": 105.4511790404,
    "VarianceExplained": 0.0055923047
  },
  "dropped_44": {
    "CumulativeVarianceExplained": 0.4980239942,
    "Mask": "Edge",
    "Method": "EdgeRegressor",
    "Retained": false,
    "SingularValue": 105.3562254526,
    "VarianceExplained": 0.005582238
  },
  "dropped_45": {
    "CumulativeVarianceExplained": 0.5035965009,
    "Mask": "Edge",
    "Method": "EdgeRegressor",
    "Retained": false,
    "SingularValue": 105.2643524957,
    "VarianceExplained": 0.0055725066
  },
  "dropped_46": {
    "CumulativeVarianceExplained": 0.5091536774,
    "Mask": "Edge",
    "Method": "EdgeRegressor",
    "Retained": false,
    "SingularValue": 105.1194608709,
    "VarianceExplained": 0.0055571766
  },
  "dropped_47": {
    "CumulativeVarianceExplained": 0.5146990211,
    "Mask": "Edge",
    "Method": "EdgeRegressor",
    "Retained": false,
    "SingularValue": 105.0074861303,
    "VarianceExplained": 0.0055453437
  },
  "dropped_48": {
    "CumulativeVarianceExplained": 0.5202178952,
    "Mask": "Edge",
    "Method": "EdgeRegressor",
    "Retained": false,
    "SingularValue": 104.756570061,
    "VarianceExplained": 0.0055188741
  },
  "dropped_49": {
    "CumulativeVarianceExplained": 0.5257288208,
    "Mask": "Edge",
    "Method": "EdgeRegressor",
    "Retained": false,
    "SingularValue": 104.6811057877,
    "VarianceExplained": 0.0055109256
  },
  "dropped_5": {
    "CumulativeVarianceExplained": 0.2678594941,
    "Mask": "Edge",
    "Method": "EdgeRegressor",
    "Retained": false,
    "SingularValue": 111.8366485679,
    "VarianceExplained": 0.0062900809
  },
  "dropped_50": {
    "CumulativeVarianceExplained": 0.5312178983,
    "Mask": "Edge",
    "Method": "EdgeRegressor",
    "Retained": false,
    "SingularValue": 104.4733944156,
    "VarianceExplained": 0.0054890774
  },
  "dropped_51": {
    "CumulativeVarianceExplained": 0.5366882929,
    "Mask": "Edge",
    "Method": "EdgeRegressor",
    "Retained": false,
    "SingularValue": 104.295448839,
    "VarianceExplained": 0.0054703947
  },
  "dropped_52": {
    "CumulativeVarianceExplained": 0.5421454002,
    "Mask": "Edge",
    "Method": "EdgeRegressor",
    "Retained": false,
    "SingularValue": 104.1687067993,
    "VarianceExplained": 0.0054571073
  },
  "dropped_53": {
    "CumulativeVarianceExplained": 0.5475995738,
    "Mask": "Edge",
    "Method": "EdgeRegressor",
    "Retained": false,
    "SingularValue": 104.1407032226,
    "VarianceExplained": 0.0054541736
  },
  "dropped_54": {
    "CumulativeVarianceExplained": 0.553030203,
    "Mask": "Edge",
    "Method": "EdgeRegressor",
    "Retained": false,
    "SingularValue": 103.9156838173,
    "VarianceExplained": 0.0054306291
  },
  "dropped_55": {
    "CumulativeVarianceExplained": 0.5584581716,
    "Mask": "Edge",
    "Method": "EdgeRegressor",
    "Retained": false,
    "SingularValue": 103.8902263398,
    "VarianceExplained": 0.0054279687
  },
  "dropped_56": {
    "CumulativeVarianceExplained": 0.5638656206,
    "Mask": "Edge",
    "Method": "EdgeRegressor",
    "Retained": false,
    "SingularValue": 103.6936689795,
    "VarianceExplained": 0.005407449
  },
  "dropped_57": {
    "CumulativeVarianceExplained": 0.5692524345,
    "Mask": "Edge",
    "Method": "EdgeRegressor",
    "Retained": false,
    "SingularValue": 103.4956300778,
    "VarianceExplained": 0.0053868139
  },
  "dropped_58": {
    "CumulativeVarianceExplained": 0.5746318719,
    "Mask": "Edge",
    "Method": "EdgeRegressor",
    "Retained": false,
    "SingularValue": 103.424744914,
    "VarianceExplained": 0.0053794375
  },
  "dropped_59": {
    "CumulativeVarianceExplained": 0.5799975183,
    "Mask": "Edge",
    "Method": "EdgeRegressor",
    "Retained": false,
    "SingularValue": 103.2920867318,
    "VarianceExplained": 0.0053656464
  },
  "dropped_6": {
    "CumulativeVarianceExplained": 0.2741166022,
    "Mask": "Edge",
    "Method": "EdgeRegressor",
    "Retained": false,
    "SingularValue": 111.5431378702,
    "VarianceExplained": 0.0062571081
  },
  "dropped_60": {
    "CumulativeVarianceExplained": 0.5853492156,
    "Mask": "Edge",
    "Method": "EdgeRegressor",
    "Retained": false,
    "SingularValue": 103.1577346377,
    "VarianceExplained": 0.0053516973
  },
  "dropped_61": {
    "CumulativeVarianceExplained": 0.5906821167,
    "Mask": "Edge",
    "Method": "EdgeRegressor",
    "Retained": false,
    "SingularValue": 102.9764208073,
    "VarianceExplained": 0.0053329011
  },
  "dropped_62": {
    "CumulativeVarianceExplained": 0.5960055675,
    "Mask": "Edge",
    "Method": "EdgeRegressor",
    "Retained": false,
    "SingularValue": 102.8851390292,
    "VarianceExplained": 0.0053234508
  },
  "dropped_63": {
    "CumulativeVarianceExplained": 0.6013257304,
    "Mask": "Edge",
    "Method": "EdgeRegressor",
    "Retained": false,
    "SingularValue": 102.8533623096,
    "VarianceExplained": 0.0053201629
  },
  "dropped_64": {
    "CumulativeVarianceExplained": 0.60661636,
    "Mask": "Edge",
    "Method": "EdgeRegressor",
    "Retained": false,
    "SingularValue": 102.5674848916,
    "VarianceExplained": 0.0052906296
  },
  "dropped_65": {
    "CumulativeVarianceExplained": 0.6118935832,
    "Mask": "Edge",
    "Method": "EdgeRegressor",
    "Retained": false,
    "SingularValue": 102.4374499908,
    "VarianceExplained": 0.0052772232
  },
  "dropped_66": {
    "CumulativeVarianceExplained": 0.617146744,
    "Mask": "Edge",
    "Method": "EdgeRegressor",
    "Retained": false,
    "SingularValue": 102.2036419901,
    "VarianceExplained": 0.0052531607
  },
  "dropped_67": {
    "CumulativeVarianceExplained": 0.6223921427,
    "Mask": "Edge",
    "Method": "EdgeRegressor",
    "Retained": false,
    "SingularValue": 102.1281064101,
    "VarianceExplained": 0.0052453987
  },
  "dropped_68": {
    "CumulativeVarianceExplained": 0.6276323176,
    "Mask": "Edge",
    "Method": "EdgeRegressor",
    "Retained": false,
    "SingularValue": 102.0772402728,
    "VarianceExplained": 0.0052401749
  },
  "dropped_69": {
    "CumulativeVarianceExplained": 0.6328592005,
    "Mask": "Edge",
    "Method": "EdgeRegressor",
    "Retained": false,
    "SingularValue": 101.9476950177,
    "VarianceExplained": 0.0052268829
  },
  "dropped_7": {
    "CumulativeVarianceExplained": 0.2803521338,
    "Mask": "Edge",
    "Method": "EdgeRegressor",
    "Retained": false,
    "SingularValue": 111.3506527345,
    "VarianceExplained": 0.0062355315
  },
  "dropped_70": {
    "CumulativeVarianceExplained": 0.6380739055,
    "Mask": "Edge",
    "Method": "EdgeRegressor",
    "Retained": false,
    "SingularValue": 101.8288646126,
    "VarianceExplained": 0.005214705
  },
  "dropped_71": {
    "CumulativeVarianceExplained": 0.6432677504,
    "Mask": "Edge",
    "Method": "EdgeRegressor",
    "Retained": false,
    "SingularValue": 101.6249893256,
    "VarianceExplained": 0.0051938448
  },
  "dropped_72": {
    "CumulativeVarianceExplained": 0.6484509379,
    "Mask": "Edge",
    "Method": "EdgeRegressor",
    "Retained": false,
    "SingularValue": 101.5206724131,
    "VarianceExplained": 0.0051831875
  },
  "dropped_73": {
    "CumulativeVarianceExplained": 0.6536258913,
    "Mask": "Edge",
    "Method": "EdgeRegressor",
    "Retained": false,
    "SingularValue": 101.4400019748,
    "VarianceExplained": 0.0051749534
  },
  "dropped_74": {
    "CumulativeVarianceExplained": 0.6587764042,
    "Mask": "Edge",
    "Method": "EdgeRegressor",
    "Retained": false,
    "SingularValue": 101.2001755742,
    "VarianceExplained": 0.0051505129
  },
  "dropped_75": {
    "CumulativeVarianceExplained": 0.663911705,
    "Mask": "Edge",
    "Method": "EdgeRegressor",
    "Retained": false,
    "SingularValue": 101.0506178954,
    "VarianceExplained": 0.0051353009
  },
  "dropped_76": {
    "CumulativeVarianceExplained": 0.6690272869,
    "Mask": "Edge",
    "Method": "EdgeRegressor",
    "Retained": false,
    "SingularValue": 100.856420185,
    "VarianceExplained": 0.0051155819
  },
  "dropped_77": {
    "CumulativeVarianceExplained": 0.6741307619,
    "Mask": "Edge",
    "Method": "EdgeRegressor",
    "Retained": false,
    "SingularValue": 100.7370016194,
    "VarianceExplained": 0.0051034749
  },
  "dropped_78": {
    "CumulativeVarianceExplained": 0.6792266388,
    "Mask": "Edge",
    "Method": "EdgeRegressor",
    "Retained": false,
    "SingularValue": 100.6619858444,
    "VarianceExplained": 0.005095877
  },
  "dropped_79": {
    "CumulativeVarianceExplained": 0.6843161179,
    "Mask": "Edge",
    "Method": "EdgeRegressor",
    "Retained": false,
    "SingularValue": 100.598774747,
    "VarianceExplained": 0.005089479
  },
  "dropped_8": {
    "CumulativeVarianceExplained": 0.2865734796,
    "Mask": "Edge",
    "Method": "EdgeRegressor",
    "Retained": false,
    "SingularValue": 111.2239208755,
    "VarianceExplained": 0.0062213459
  },
  "dropped_80": {
    "CumulativeVarianceExplained": 0.6893977462,
    "Mask": "Edge",
    "Method": "EdgeRegressor",
    "Retained": false,
    "SingularValue": 100.5211567511,
    "VarianceExplained": 0.0050816284
  },
  "dropped_81": {
    "CumulativeVarianceExplained": 0.6944672629,
    "Mask": "Edge",
    "Method": "EdgeRegressor",
    "Retained": false,
    "SingularValue": 100.4012926965,
    "VarianceExplained": 0.0050695167
  },
  "dropped_82": {
    "CumulativeVarianceExplained": 0.6995192369,
    "Mask": "Edge",
    "Method": "EdgeRegressor",
    "Retained": false,
    "SingularValue": 100.2274266611,
    "VarianceExplained": 0.005051974
  },
  "dropped_83": {
    "CumulativeVarianceExplained": 0.7045635802,
    "Mask": "Edge",
    "Method": "EdgeRegressor",
    "Retained": false,
    "SingularValue": 100.1517048882,
    "VarianceExplained": 0.0050443433
  },
  "dropped_84": {
    "CumulativeVarianceExplained": 0.7095900712,
    "Mask": "Edge",
    "Method": "EdgeRegressor",
    "Retained": false,
    "SingularValue": 99.9743246279,
    "VarianceExplained": 0.0050264909
  },
  "dropped_85": {
    "CumulativeVarianceExplained": 0.7146084135,
    "Mask": "Edge",
    "Method": "EdgeRegressor",
    "Retained": false,
    "SingularValue": 99.89325643,
    "VarianceExplained": 0.0050183424
  },
  "dropped_86": {
    "CumulativeVarianceExplained": 0.7196176502,
    "Mask": "Edge",
    "Method": "EdgeRegressor",
    "Retained": false,
    "SingularValue": 99.8025875024,
    "VarianceExplained": 0.0050092366
  },
  "dropped_87": {
    "CumulativeVarianceExplained": 0.7246079566,
    "Mask": "Edge",
    "Method": "EdgeRegressor",
    "Retained": false,
    "SingularValue": 99.6138289504,
    "VarianceExplained": 0.0049903064
  },
  "dropped_88": {
    "CumulativeVarianceExplained": 0.7295809808,
    "Mask": "Edge",
    "Method": "EdgeRegressor",
    "Retained": false,
    "SingularValue": 99.4411901544,
    "VarianceExplained": 0.0049730242
  },
  "dropped_89": {
    "CumulativeVarianceExplained": 0.7345345559,
    "Mask": "Edge",
    "Method": "EdgeRegressor",
    "Retained": false,
    "SingularValue": 99.2465465443,
    "VarianceExplained": 0.0049535751
  },
  "dropped_9": {
    "CumulativeVarianceExplained": 0.292777039,
    "Mask": "Edge",
    "Method": "EdgeRegressor",
    "Retained": false,
    "SingularValue": 111.0648153387,
    "VarianceExplained": 0.0062035594
  },
  "dropped_90": {
    "CumulativeVarianceExplained": 0.7394793188,
    "Mask": "Edge",
    "Method": "EdgeRegressor",
    "Retained": false,
    "SingularValue": 99.1582294667,
    "VarianceExplained": 0.0049447629
  },
  "dropped_91": {
    "CumulativeVarianceExplained": 0.7444169009,
    "Mask": "Edge",
    "Method": "EdgeRegressor",
    "Retained": false,
    "SingularValue": 99.0862038487,
    "VarianceExplained": 0.0049375821
  },
  "dropped_92": {
    "CumulativeVarianceExplained": 0.7493433005,
    "Mask": "Edge",
    "Method": "EdgeRegressor",
    "Retained": false,
    "SingularValue": 98.9739370262,
    "VarianceExplained": 0.0049263996
  },
  "dropped_93": {
    "CumulativeVarianceExplained": 0.7542606561,
    "Mask": "Edge",
    "Method": "EdgeRegressor",
    "Retained": false,
    "SingularValue": 98.8830459025,
    "VarianceExplained": 0.0049173556
  },
  "dropped_94": {
    "CumulativeVarianceExplained": 0.7591679349,
    "Mask": "Edge",
    "Method": "EdgeRegressor",
    "Retained": false,
    "SingularValue": 98.7816760143,
    "VarianceExplained": 0.0049072787
  },
  "dropped_95": {
    "CumulativeVarianceExplained": 0.7640491291,
    "Mask": "Edge",
    "Method": "EdgeRegressor",
    "Retained": false,
    "SingularValue": 98.5187909738,
    "VarianceExplained": 0.0048811943
  },
  "dropped_96": {
    "CumulativeVarianceExplained": 0.7689241775,
    "Mask": "Edge",
    "Method": "EdgeRegressor",
    "Retained": false,
    "SingularValue": 98.4567490182,
    "VarianceExplained": 0.0048750484
  },
  "dropped_97": {
    "CumulativeVarianceExplained": 0.7737857103,
    "Mask": "Edge",
    "Method": "EdgeRegressor",
    "Retained": false,
    "SingularValue": 98.3201734372,
    "VarianceExplained": 0.0048615328
  },
  "dropped_98": {
    "CumulativeVarianceExplained": 0.7786370991,
    "Mask": "Edge",
    "Method": "EdgeRegressor",
    "Retained": false,
    "SingularValue": 98.2175436086,
    "VarianceExplained": 0.0048513888
  },
  "dropped_99": {
    "CumulativeVarianceExplained": 0.7834720155,
    "Mask": "Edge",
    "Method": "EdgeRegressor",
    "Retained": false,
    "SingularValue": 98.0506580604,
    "VarianceExplained": 0.0048349164
  },
  "edge_comp_00": {
    "CumulativeVarianceExplained": 0.0236645402,
    "Mask": "Edge",
    "Method": "EdgeRegressor",
    "Retained": true,
    "SingularValue": 216.9227302634,
    "VarianceExplained": 0.0236645402
  },
  "edge_comp_01": {
    "CumulativeVarianceExplained": 0.0433386657,
    "Mask": "Edge",
    "Method": "EdgeRegressor",
    "Retained": true,
    "SingularValue": 197.7897337405,
    "VarianceExplained": 0.0196741255
  },
  "edge_comp_02": {
    "CumulativeVarianceExplained": 0.0607739259,
    "Mask": "Edge",
    "Method": "EdgeRegressor",
    "Retained": true,
    "SingularValue": 186.1959560669,
    "VarianceExplained": 0.0174352603
  },
  "edge_comp_03": {
    "CumulativeVarianceExplained": 0.0771849838,
    "Mask": "Edge",
    "Method": "EdgeRegressor",
    "Retained": true,
    "SingularValue": 180.644321824,
    "VarianceExplained": 0.0164110578
  },
  "edge_comp_04": {
    "CumulativeVarianceExplained": 0.0879036671,
    "Mask": "Edge",
    "Method": "EdgeRegressor",
    "Retained": true,
    "SingularValue": 145.9912230599,
    "VarianceExplained": 0.0107186833
  },
  "edge_comp_05": {
    "CumulativeVarianceExplained": 0.0974804846,
    "Mask": "Edge",
    "Method": "EdgeRegressor",
    "Retained": true,
    "SingularValue": 137.9960433251,
    "VarianceExplained": 0.0095768176
  },
  "edge_comp_06": {
    "CumulativeVarianceExplained": 0.1067472815,
    "Mask": "Edge",
    "Method": "EdgeRegressor",
    "Retained": true,
    "SingularValue": 135.7440645762,
    "VarianceExplained": 0.0092667969
  },
  "edge_comp_07": {
    "CumulativeVarianceExplained": 0.1155653634,
    "Mask": "Edge",
    "Method": "EdgeRegressor",
    "Retained": true,
    "SingularValue": 132.4168004942,
    "VarianceExplained": 0.0088180819
  },
  "edge_comp_08": {
    "CumulativeVarianceExplained": 0.1239868718,
    "Mask": "Edge",
    "Method": "EdgeRegressor",
    "Retained": true,
    "SingularValue": 129.4049740215,
    "VarianceExplained": 0.0084215084
  },
  "edge_comp_09": {
    "CumulativeVarianceExplained": 0.1319640815,
    "Mask": "Edge",
    "Method": "EdgeRegressor",
    "Retained": true,
    "SingularValue": 125.9451743876,
    "VarianceExplained": 0.0079772097
  },
  "edge_comp_10": {
    "CumulativeVarianceExplained": 0.1398762083,
    "Mask": "Edge",
    "Method": "EdgeRegressor",
    "Retained": true,
    "SingularValue": 125.4303537656,
    "VarianceExplained": 0.0079121268
  },
  "edge_comp_11": {
    "CumulativeVarianceExplained": 0.1473251963,
    "Mask": "Edge",
    "Method": "EdgeRegressor",
    "Retained": true,
    "SingularValue": 121.7039473354,
    "VarianceExplained": 0.007448988
  },
  "edge_comp_12": {
    "CumulativeVarianceExplained": 0.1546391854,
    "Mask": "Edge",
    "Method": "EdgeRegressor",
    "Retained": true,
    "SingularValue": 120.5960767155,
    "VarianceExplained": 0.007313989
  },
  "edge_comp_13": {
    "CumulativeVarianceExplained": 0.1618659189,
    "Mask": "Edge",
    "Method": "EdgeRegressor",
    "Retained": true,
    "SingularValue": 119.8745658658,
    "VarianceExplained": 0.0072267335
  },
  "edge_comp_14": {
    "CumulativeVarianceExplained": 0.1689516171,
    "Mask": "Edge",
    "Method": "EdgeRegressor",
    "Retained": true,
    "SingularValue": 118.6990799545,
    "VarianceExplained": 0.0070856982
  },
  "edge_comp_15": {
    "CumulativeVarianceExplained": 0.1759773332,
    "Mask": "Edge",
    "Method": "EdgeRegressor",
    "Retained": true,
    "SingularValue": 118.1956047598,
    "VarianceExplained": 0.0070257162
  },
  "edge_comp_16": {
    "CumulativeVarianceExplained": 0.182930376,
    "Mask": "Edge",
    "Method": "EdgeRegressor",
    "Retained": true,
    "SingularValue": 117.5827132778,
    "VarianceExplained": 0.0069530428
  },
  "edge_comp_17": {
    "CumulativeVarianceExplained": 0.1898016832,
    "Mask": "Edge",
    "Method": "EdgeRegressor",
    "Retained": true,
    "SingularValue": 116.8895561392,
    "VarianceExplained": 0.0068713072
  },
  "edge_comp_18": {
    "CumulativeVarianceExplained": 0.1965882723,
    "Mask": "Edge",
    "Method": "EdgeRegressor",
    "Retained": true,
    "SingularValue": 116.1667410184,
    "VarianceExplained": 0.0067865891
  },
  "edge_comp_19": {
    "CumulativeVarianceExplained": 0.2033149035,
    "Mask": "Edge",
    "Method": "EdgeRegressor",
    "Retained": true,
    "SingularValue": 115.652449096,
    "VarianceExplained": 0.0067266311
  },
  "edge_comp_20": {
    "CumulativeVarianceExplained": 0.2099996861,
    "Mask": "Edge",
    "Method": "EdgeRegressor",
    "Retained": true,
    "SingularValue": 115.2921323128,
    "VarianceExplained": 0.0066847826
  },
  "edge_comp_21": {
    "CumulativeVarianceExplained": 0.2165807896,
    "Mask": "Edge",
    "Method": "EdgeRegressor",
    "Retained": true,
    "SingularValue": 114.3945641844,
    "VarianceExplained": 0.0065811035
  },
  "edge_comp_22": {
    "CumulativeVarianceExplained": 0.2231204605,
    "Mask": "Edge",
    "Method": "EdgeRegressor",
    "Retained": true,
    "SingularValue": 114.0338986052,
    "VarianceExplained": 0.0065396709
  },
  "edge_comp_23": {
    "CumulativeVarianceExplained": 0.2296122774,
    "Mask": "Edge",
    "Method": "EdgeRegressor",
    "Retained": true,
    "SingularValue": 113.6159121203,
    "VarianceExplained": 0.0064918169
  },
  "framewise_displacement": {
    "Units": "mm"
  },
  "rot_x": {
    "Description": "Rotation about left-right axis. Also known as \"pitch\".",
    "Units": "rad"
  },
  "rot_y": {
    "Description": "Rotation about anterior-posterior axis. Also known as \"roll\".",
    "Units": "rad"
  },
  "rot_z": {
    "Description": "Rotation about superior-inferior axis. Also known as \"yaw\".",
    "Units": "rad"
  },
  "t_comp_cor_00": {
    "CumulativeVarianceExplained": 0.1918018285,
    "Method": "tCompCor",
    "Retained": true,
    "SingularValue": 159.5900410617,
    "VarianceExplained": 0.1918018285
  },
  "t_comp_cor_01": {
    "CumulativeVarianceExplained": 0.3026095727,
    "Method": "tCompCor",
    "Retained": true,
    "SingularValue": 121.3010252665,
    "VarianceExplained": 0.1108077442
  },
  "t_comp_cor_02": {
    "CumulativeVarianceExplained": 0.3802928025,
    "Method": "tCompCor",
    "Retained": true,
    "SingularValue": 101.564761249,
    "VarianceExplained": 0.0776832299
  },
  "t_comp_cor_03": {
    "CumulativeVarianceExplained": 0.4350698935,
    "Method": "tCompCor",
    "Retained": true,
    "SingularValue": 85.2862260532,
    "VarianceExplained": 0.054777091
  },
  "t_comp_cor_04": {
    "CumulativeVarianceExplained": 0.4809073251,
    "Method": "tCompCor",
    "Retained": true,
    "SingularValue": 78.0170549712,
    "VarianceExplained": 0.0458374316
  },
  "t_comp_cor_05": {
    "CumulativeVarianceExplained": 0.513966691,
    "Method": "tCompCor",
    "Retained": true,
    "SingularValue": 66.2562229078,
    "VarianceExplained": 0.0330593659
  },
  "trans_x": {
    "Description": "Translation along left-right axis.",
    "Units": "mm"
  },
  "trans_y": {
    "Description": "Translation along anterior-posterior axis.",
    "Units": "mm"
  },
  "trans_z": {
    "Description": "Translation along superior-inferior axis.",
    "Units": "mm"
  },
  "w_comp_cor_00": {
    "CumulativeVarianceExplained": 0.011576148,
    "Mask": "WM",
    "Method": "aCompCor",
    "Retained": true,
    "SingularValue": 49.4766465825,
    "VarianceExplained": 0.011576148
  },
  "w_comp_cor_01": {
    "CumulativeVarianceExplained": 0.0227916776,
    "Mask": "WM",
    "Method": "aCompCor",
    "Retained": true,
    "SingularValue": 48.6999049926,
    "VarianceExplained": 0.0112155296
  },
  "w_comp_cor_02": {
    "CumulativeVarianceExplained": 0.0337056154,
    "Mask": "WM",
    "Method": "aCompCor",
    "Retained": true,
    "SingularValue": 48.0406593046,
    "VarianceExplained": 0.0109139378
  },
  "w_comp_cor_03": {
    "CumulativeVarianceExplained": 0.0446080408,
    "Mask": "WM",
    "Method": "aCompCor",
    "Retained": true,
    "SingularValue": 48.0153152694,
    "VarianceExplained": 0.0109024255
  },
  "w_comp_cor_04": {
    "CumulativeVarianceExplained": 0.0552527171,
    "Mask": "WM",
    "Method": "aCompCor",
    "Retained": true,
    "SingularValue": 47.4443445321,
    "VarianceExplained": 0.0106446763
  },
  "w_comp_cor_05": {
    "CumulativeVarianceExplained": 0.0657156537,
    "Mask": "WM",
    "Method": "aCompCor",
    "Retained": true,
    "SingularValue": 47.0375850399,
    "VarianceExplained": 0.0104629365
  },
  "w_comp_cor_06": {
    "CumulativeVarianceExplained": 0.0760747631,
    "Mask": "WM",
    "Method": "aCompCor",
    "Retained": true,
    "SingularValue": 46.8036185743,
    "VarianceExplained": 0.0103591094
  },
  "w_comp_cor_07": {
    "CumulativeVarianceExplained": 0.0861993301,
    "Mask": "WM",
    "Method": "aCompCor",
    "Retained": true,
    "SingularValue": 46.2707406246,
    "VarianceExplained": 0.010124567
  },
  "w_comp_cor_08": {
    "CumulativeVarianceExplained": 0.0962812835,
    "Mask": "WM",
    "Method": "aCompCor",
    "Retained": true,
    "SingularValue": 46.1732627246,
    "VarianceExplained": 0.0100819534
  },
  "w_comp_cor_09": {
    "CumulativeVarianceExplained": 0.106319461,
    "Mask": "WM",
    "Method": "aCompCor",
    "Retained": true,
    "SingularValue": 46.0729115549,
    "VarianceExplained": 0.0100381776
  },
  "w_comp_cor_10": {
    "CumulativeVarianceExplained": 0.1162491882,
    "Mask": "WM",
    "Method": "aCompCor",
    "Retained": true,
    "SingularValue": 45.8233546735,
    "VarianceExplained": 0.0099297272
  },
  "w_comp_cor_11": {
    "CumulativeVarianceExplained": 0.12603748,
    "Mask": "WM",
    "Method": "aCompCor",
    "Retained": true,
    "SingularValue": 45.4958386959,
    "VarianceExplained": 0.0097882918
  },
  "w_comp_cor_12": {
    "CumulativeVarianceExplained": 0.1356894476,
    "Mask": "WM",
    "Method": "aCompCor",
    "Retained": true,
    "SingularValue": 45.1779113304,
    "VarianceExplained": 0.0096519676
  },
  "w_comp_cor_13": {
    "CumulativeVarianceExplained": 0.1452254578,
    "Mask": "WM",
    "Method": "aCompCor",
    "Retained": true,
    "SingularValue": 44.905710748,
    "VarianceExplained": 0.0095360102
  },
  "w_comp_cor_14": {
    "CumulativeVarianceExplained": 0.154635144,
    "Mask": "WM",
    "Method": "aCompCor",
    "Retained": true,
    "SingularValue": 44.6072851509,
    "VarianceExplained": 0.0094096862
  },
  "w_comp_cor_15": {
    "CumulativeVarianceExplained": 0.1639976419,
    "Mask": "WM",
    "Method": "aCompCor",
    "Retained": true,
    "SingularValue": 44.4952946891,
    "VarianceExplained": 0.0093624979
  },
  "w_comp_cor_16": {
    "CumulativeVarianceExplained": 0.173337004,
    "Mask": "WM",
    "Method": "aCompCor",
    "Retained": true,
    "SingularValue": 44.440284366,
    "VarianceExplained": 0.0093393621
  },
  "w_comp_cor_17": {
    "CumulativeVarianceExplained": 0.1824423861,
    "Mask": "WM",
    "Method": "aCompCor",
    "Retained": true,
    "SingularValue": 43.880069631,
    "VarianceExplained": 0.0091053821
  },
  "w_comp_cor_18": {
    "CumulativeVarianceExplained": 0.1915045658,
    "Mask": "WM",
    "Method": "aCompCor",
    "Retained": true,
    "SingularValue": 43.7758468176,
    "VarianceExplained": 0.0090621797
  },
  "w_comp_cor_19": {
    "CumulativeVarianceExplained": 0.2004697606,
    "Mask": "WM",
    "Method": "aCompCor",
    "Retained": true,
    "SingularValue": 43.5409688791,
    "VarianceExplained": 0.0089651949
  },
  "w_comp_cor_20": {
    "CumulativeVarianceExplained": 0.2093691643,
    "Mask": "WM",
    "Method": "aCompCor",
    "Retained": true,
    "SingularValue": 43.3809115919,
    "VarianceExplained": 0.0088994036
  },
  "w_comp_cor_21": {
    "CumulativeVarianceExplained": 0.2182121425,
    "Mask": "WM",
    "Method": "aCompCor",
    "Retained": true,
    "SingularValue": 43.24316765,
    "VarianceExplained": 0.0088429782
  },
  "w_comp_cor_22": {
    "CumulativeVarianceExplained": 0.2269648951,
    "Mask": "WM",
    "Method": "aCompCor",
    "Retained": true,
    "SingularValue": 43.0219952479,
    "VarianceExplained": 0.0087527526
  },
  "w_comp_cor_23": {
    "CumulativeVarianceExplained": 0.2356459329,
    "Mask": "WM",
    "Method": "aCompCor",
    "Retained": true,
    "SingularValue": 42.8453844593,
    "VarianceExplained": 0.0086810378
  },
  "w_comp_cor_24": {
    "CumulativeVarianceExplained": 0.2443081229,
    "Mask": "WM",
    "Method": "aCompCor",
    "Retained": true,
    "SingularValue": 42.7988476351,
    "VarianceExplained": 0.0086621901
  },
  "w_comp_cor_25": {
    "CumulativeVarianceExplained": 0.2528765535,
    "Mask": "WM",
    "Method": "aCompCor",
    "Retained": true,
    "SingularValue": 42.5665901308,
    "VarianceExplained": 0.0085684305
  },
  "w_comp_cor_26": {
    "CumulativeVarianceExplained": 0.2613443227,
    "Mask": "WM",
    "Method": "aCompCor",
    "Retained": true,
    "SingularValue": 42.3158167753,
    "VarianceExplained": 0.0084677692
  },
  "w_comp_cor_27": {
    "CumulativeVarianceExplained": 0.2697288211,
    "Mask": "WM",
    "Method": "aCompCor",
    "Retained": true,
    "SingularValue": 42.1072388538,
    "VarianceExplained": 0.0083844984
  },
  "w_comp_cor_28": {
    "CumulativeVarianceExplained": 0.2780925914,
    "Mask": "WM",
    "Method": "aCompCor",
    "Retained": true,
    "SingularValue": 42.0551581032,
    "VarianceExplained": 0.0083637703
  },
  "w_comp_cor_29": {
    "CumulativeVarianceExplained": 0.2863899392,
    "Mask": "WM",
    "Method": "aCompCor",
    "Retained": true,
    "SingularValue": 41.8878306905,
    "VarianceExplained": 0.0082973478
  },
  "w_comp_cor_30": {
    "CumulativeVarianceExplained": 0.2946713398,
    "Mask": "WM",
    "Method": "aCompCor",
    "Retained": true,
    "SingularValue": 41.8475579114,
    "VarianceExplained": 0.0082814006
  },
  "w_comp_cor_31": {
    "CumulativeVarianceExplained": 0.3028279152,
    "Mask": "WM",
    "Method": "aCompCor",
    "Retained": true,
    "SingularValue": 41.5309770531,
    "VarianceExplained": 0.0081565754
  },
  "w_comp_cor_32": {
    "CumulativeVarianceExplained": 0.3109647581,
    "Mask": "WM",
    "Method": "aCompCor",
    "Retained": true,
    "SingularValue": 41.4807105172,
    "VarianceExplained": 0.0081368429
  },
  "w_comp_cor_33": {
    "CumulativeVarianceExplained": 0.3190343183,
    "Mask": "WM",
    "Method": "aCompCor",
    "Retained": true,
    "SingularValue": 41.3088547448,
    "VarianceExplained": 0.0080695602
  },
  "w_comp_cor_34": {
    "CumulativeVarianceExplained": 0.3270318807,
    "Mask": "WM",
    "Method": "aCompCor",
    "Retained": true,
    "SingularValue": 41.1241599745,
    "VarianceExplained": 0.0079975624
  },
  "w_comp_cor_35": {
    "CumulativeVarianceExplained": 0.3349752675,
    "Mask": "WM",
    "Method": "aCompCor",
    "Retained": true,
    "SingularValue": 40.9846354899,
    "VarianceExplained": 0.0079433868
  },
  "w_comp_cor_36": {
    "CumulativeVarianceExplained": 0.3428962206,
    "Mask": "WM",
    "Method": "aCompCor",
    "Retained": true,
    "SingularValue": 40.9267202635,
    "VarianceExplained": 0.0079209531
  },
  "w_comp_cor_37": {
    "CumulativeVarianceExplained": 0.3507565628,
    "Mask": "WM",
    "Method": "aCompCor",
    "Retained": true,
    "SingularValue": 40.7698345803,
    "VarianceExplained": 0.0078603422
  },
  "w_comp_cor_38": {
    "CumulativeVarianceExplained": 0.3585565361,
    "Mask": "WM",
    "Method": "aCompCor",
    "Retained": true,
    "SingularValue": 40.612972601,
    "VarianceExplained": 0.0077999733
  },
  "w_comp_cor_39": {
    "CumulativeVarianceExplained": 0.3663108983,
    "Mask": "WM",
    "Method": "aCompCor",
    "Retained": true,
    "SingularValue": 40.4940546151,
    "VarianceExplained": 0.0077543623
  },
  "w_comp_cor_40": {
    "CumulativeVarianceExplained": 0.3739733256,
    "Mask": "WM",
    "Method": "aCompCor",
    "Retained": true,
    "SingularValue": 40.2532918735,
    "VarianceExplained": 0.0076624272
  },
  "w_comp_cor_41": {
    "CumulativeVarianceExplained": 0.3815429521,
    "Mask": "WM",
    "Method": "aCompCor",
    "Retained": true,
    "SingularValue": 40.0087928864,
    "VarianceExplained": 0.0075696265
  },
  "w_comp_cor_42": {
    "CumulativeVarianceExplained": 0.3890828212,
    "Mask": "WM",
    "Method": "aCompCor",
    "Retained": true,
    "SingularValue": 39.9300749019,
    "VarianceExplained": 0.0075398691
  },
  "w_comp_cor_43": {
    "CumulativeVarianceExplained": 0.3964517463,
    "Mask": "WM",
    "Method": "aCompCor",
    "Retained": true,
    "SingularValue": 39.4748320638,
    "VarianceExplained": 0.007368925
  },
  "w_comp_cor_44": {
    "CumulativeVarianceExplained": 0.4038086248,
    "Mask": "WM",
    "Method": "aCompCor",
    "Retained": true,
    "SingularValue": 39.4425528266,
    "VarianceExplained": 0.0073568786
  },
  "w_comp_cor_45": {
    "CumulativeVarianceExplained": 0.411099388,
    "Mask": "WM",
    "Method": "aCompCor",
    "Retained": true,
    "SingularValue": 39.2649199993,
    "VarianceExplained": 0.0072907632
  },
  "w_comp_cor_46": {
    "CumulativeVarianceExplained": 0.4183674008,
    "Mask": "WM",
    "Method": "aCompCor",
    "Retained": true,
    "SingularValue": 39.203610184,
    "VarianceExplained": 0.0072680128
  },
  "w_comp_cor_47": {
    "CumulativeVarianceExplained": 0.4256057021,
    "Mask": "WM",
    "Method": "aCompCor",
    "Retained": true,
    "SingularValue": 39.123396386,
    "VarianceExplained": 0.0072383013
  },
  "w_comp_cor_48": {
    "CumulativeVarianceExplained": 0.4327636543,
    "Mask": "WM",
    "Method": "aCompCor",
    "Retained": true,
    "SingularValue": 38.905644914,
    "VarianceExplained": 0.0071579522
  },
  "w_comp_cor_49": {
    "CumulativeVarianceExplained": 0.4398782792,
    "Mask": "WM",
    "Method": "aCompCor",
    "Retained": true,
    "SingularValue": 38.7877177688,
    "VarianceExplained": 0.0071146249
  },
  "w_comp_cor_50": {
    "CumulativeVarianceExplained": 0.4469136874,
    "Mask": "WM",
    "Method": "aCompCor",
    "Retained": true,
    "SingularValue": 38.571175021,
    "VarianceExplained": 0.0070354081
  },
  "w_comp_cor_51": {
    "CumulativeVarianceExplained": 0.4538947832,
    "Mask": "WM",
    "Method": "aCompCor",
    "Retained": true,
    "SingularValue": 38.4220047034,
    "VarianceExplained": 0.0069810958
  },
  "w_comp_cor_52": {
    "CumulativeVarianceExplained": 0.4608479298,
    "Mask": "WM",
    "Method": "aCompCor",
    "Retained": true,
    "SingularValue": 38.3450152047,
    "VarianceExplained": 0.0069531466
  },
  "w_comp_cor_53": {
    "CumulativeVarianceExplained": 0.4677882102,
    "Mask": "WM",
    "Method": "aCompCor",
    "Retained": true,
    "SingularValue": 38.3095217911,
    "VarianceExplained": 0.0069402804
  },
  "w_comp_cor_54": {
    "CumulativeVarianceExplained": 0.4746833133,
    "Mask": "WM",
    "Method": "aCompCor",
    "Retained": true,
    "SingularValue": 38.1846316149,
    "VarianceExplained": 0.0068951031
  },
  "w_comp_cor_55": {
    "CumulativeVarianceExplained": 0.481492656,
    "Mask": "WM",
    "Method": "aCompCor",
    "Retained": true,
    "SingularValue": 37.9464205024,
    "VarianceExplained": 0.0068093426
  },
  "w_comp_cor_56": {
    "CumulativeVarianceExplained": 0.4882820703,
    "Mask": "WM",
    "Method": "aCompCor",
    "Retained": true,
    "SingularValue": 37.8908526399,
    "VarianceExplained": 0.0067894143
  },
  "w_comp_cor_57": {
    "CumulativeVarianceExplained": 0.4950395949,
    "Mask": "WM",
    "Method": "aCompCor",
    "Retained": true,
    "SingularValue": 37.80176176,
    "VarianceExplained": 0.0067575246
  },
  "w_comp_cor_58": {
    "CumulativeVarianceExplained": 0.5017141313,
    "Mask": "WM",
    "Method": "aCompCor",
    "Retained": true,
    "SingularValue": 37.5689253213,
    "VarianceExplained": 0.0066745363
  }
}